lsiwh37249_cmd/__init__.py
lsiwh37249_cmd/cmd.py
lsiwh37249_cmd-0.2.1.dist-info/METADATA
lsiwh37249_cmd-0.2.1.dist-info/WHEEL
lsiwh37249_cmd-0.2.1.dist-info/entry_points.txt
lsiwh37249_cmd-0.2.1.dist-info/top_level.txt
lsiwh37249_cmd-0.2.1.dist-info/RECORD
