Metadata-Version: 2.1
Name: lsiwh37249_cmd
Version: 0.2.1
Summary: 의존성 추가
Author-email: lsiwh37249 <lsiwh37249@gmail.com>
License: MIT
Requires-Python: >=3.9
Requires-Dist: lsiwh37249-lotto >=0.2.0
